sageutils/__init__.py
sageutils/passutils.py
sageutils-0.1.8.data/scripts/passutil
sageutils-0.1.8.dist-info/LICENSE
sageutils-0.1.8.dist-info/METADATA
sageutils-0.1.8.dist-info/WHEEL
sageutils-0.1.8.dist-info/top_level.txt
sageutils-0.1.8.dist-info/RECORD
