Metadata-Version: 2.1
Name: sageutils
Version: 0.1.8
Summary: Sage common utilities library
Home-page: https://github.com/ttong-ai/sageutils
Author: Tony Tong
Author-email: ttong@pro-ai.org
License: MIT
Project-URL: Bug Tracker, https://github.com/ttong-ai/sageutils/issues
Platform: UNKNOWN
Classifier: Programming Language :: Python :: 3
Classifier: License :: OSI Approved :: MIT License
Classifier: Operating System :: OS Independent
Requires-Python: >=3.6, <4.0
Requires-Dist: cryptography
Requires-Dist: fire
